pyhealthify/__init__.py
pyhealthify/activity.py
pyhealthify/bmi.py
pyhealthify/calories.py
pyhealthify/hydration.py
pyhealthify-0.1.1.dist-info/licenses/LICENSE
pyhealthify-0.1.1.dist-info/METADATA
pyhealthify-0.1.1.dist-info/WHEEL
pyhealthify-0.1.1.dist-info/top_level.txt
pyhealthify-0.1.1.dist-info/RECORD
