Metadata-Version: 2.4
Name: pyhealthify
Version: 0.1.1
Summary: A simple health & fitness utility library (BMI, calories, macros, hydration).
Home-page: https://github.com/ArpitChb2704/PyHealthify
Author: Arpit Chhabra
Author-email: arpitchhabra2704@gmail.com
License: MIT
Classifier: Programming Language :: Python :: 3
Classifier: Intended Audience :: Developers
Classifier: Topic :: Software Development :: Libraries
Classifier: License :: OSI Approved :: MIT License
Classifier: Operating System :: OS Independent
Requires-Python: >=3.7
License-File: LICENSE
Dynamic: author
Dynamic: author-email
Dynamic: classifier
Dynamic: description
Dynamic: description-content-type
Dynamic: home-page
Dynamic: license
Dynamic: license-file
Dynamic: requires-python
Dynamic: summary
